README.md
setup.py
android_backup/__init__.py
android_backup/android_backup.py
android_backup/pack.py
android_backup/unpack.py
android_backup.egg-info/PKG-INFO
android_backup.egg-info/SOURCES.txt
android_backup.egg-info/dependency_links.txt
android_backup.egg-info/entry_points.txt
android_backup.egg-info/top_level.txt