Metadata-Version: 1.1
Name: android-backup
Version: 0.0.1
Summary: Unpack and repack android backups
Home-page: https://github.com/bluec0re/android-backup-tools
Author: BlueC0re
Author-email: bluec0re@users.noreply.github.com
License: Apache-2.0
Keywords: android backup pack unpack development
Platform: UNKNOWN
Classifier: Development Status :: 3 - Alpha
Classifier: Intended Audience :: Developers
Classifier: License :: OSI Approved :: Apache Software License
Classifier: Programming Language :: Python :: 2
Classifier: Programming Language :: Python :: 3
